lvfs/__init__.py
lvfs/__main__.py
lvfs/artifactory.py
lvfs/credentials.py
lvfs/gcs.py
lvfs/hdfsclioverssh.py
lvfs/hdfsoverssh.py
lvfs/local.py
lvfs/minio.py
lvfs/stat.py
lvfs/url.py
lvfs/vault.py
lvfs-1.1.2.dist-info/WHEEL
lvfs-1.1.2.dist-info/METADATA
lvfs-1.1.2.dist-info/RECORD
