Metadata-Version: 2.1
Name: lvfs
Version: 1.1.2
Summary: Convenient high level file IO across multiple protocols
Home-page: https://github.com/lowes
Author: Lowe's Companies, Inc.
Author-email:  lowesopensource@lowes.com
Requires-Python: >=3.7
Classifier: License :: OSI Approved :: MIT License
Requires-Dist: pandas ~= 1.0
Requires-Dist: pyyaml ~= 5.3
Requires-Dist: hvac ~= 0.10
Requires-Dist: keyring ~= 21.5
Requires-Dist: python-dotenv ~= 0.15.0
Requires-Dist: aiofiles >= 0.5.0
Requires-Dist: pyarrow >= 0.13.0
Requires-Dist: pybind11 ~= 2.6.0
Requires-Dist: google-cloud-storage ~= 1.29 ; extra == "all"
Requires-Dist: minio ~= 6.0 ; extra == "all"
Requires-Dist: hdfs ~= 2.5 ; extra == "all"
Requires-Dist: paramiko ~= 2.7.1 ; extra == "all"
Requires-Dist: PySocks ~= 1.7 ; extra == "all"
Requires-Dist: requests ~= 2.23 ; extra == "all"
Requires-Dist: pyorc ~= 0.4.0 ; extra == "all"
Requires-Dist: gssapi ~= 1.6.12 ; extra == "all"
Requires-Dist: requests-gssapi ~= 1.2.3 ; extra == "all"
Requires-Dist: google-cloud-storage ~= 1.29 ; extra == "gcs"
Requires-Dist: hdfs ~= 2.5 ; extra == "hdfs"
Requires-Dist: paramiko ~= 2.7.1 ; extra == "hdfs"
Requires-Dist: PySocks ~= 1.7 ; extra == "hdfs"
Requires-Dist: requests ~= 2.23 ; extra == "hdfs"
Requires-Dist: minio ~= 6.0 ; extra == "minio"
Requires-Dist: pytest-benchmark ~= 3.0 ; extra == "test"
Requires-Dist: pytest-timeout ~= 1.4 ; extra == "test"
Requires-Dist: pytest-asyncio ~= 0.14.0 ; extra == "test"
Requires-Dist: pytest ~= 6.0 ; extra == "test"
Provides-Extra: all
Provides-Extra: gcs
Provides-Extra: hdfs
Provides-Extra: minio
Provides-Extra: test
